autodistill_palm2/__init__.py
autodistill_palm2-0.0.1.dist-info/METADATA
autodistill_palm2-0.0.1.dist-info/WHEEL
autodistill_palm2-0.0.1.dist-info/top_level.txt
autodistill_palm2-0.0.1.dist-info/RECORD
